Metadata-Version: 2.1
Name: python-miniproject-package
Version: 1.0.1
Summary: A fully programmable user-land ecosystem purely on Python for deployment on IoT boards like RaspberryPi and BeagleBone.
Home-page: https://git.corp.adobe.com/priyanss/python-mini-project
Author: Samridhi Chaubey
License: MIT
Platform: UNKNOWN
Classifier: License :: OSI Approved :: MIT License
Classifier: Programming Language :: Python :: 3
Classifier: Programming Language :: Python :: 3.6
